LICENSE
MANIFEST.in
README.rst
requirements-dev.txt
requirements.txt
setup.py
btsync/__init__.py
btsync/client.py
btsync/models.py
btsync.py.egg-info/PKG-INFO
btsync.py.egg-info/SOURCES.txt
btsync.py.egg-info/dependency_links.txt
btsync.py.egg-info/not-zip-safe
btsync.py.egg-info/requires.txt
btsync.py.egg-info/top_level.txt