Metadata-Version: 1.1
Name: btsync.py
Version: 0.9.9
Summary: A Python API client for BitTorrent Sync
Home-page: https://github.com/kevinjqiu/btsync.py
Author: Kevin Jing Qiu
Author-email: kevin.jing.qiu@gmail.com
License: MIT
Keywords: api
Platform: UNKNOWN
Classifier: Intended Audience :: Developers
Classifier: Environment :: Console
Classifier: License :: OSI Approved :: MIT License
Classifier: Programming Language :: Python :: 2.6
Classifier: Programming Language :: Python :: 2.7
Classifier: Topic :: Software Development :: Libraries :: Application Frameworks
